painkill.py
painkill-0.0.1.dist-info/METADATA
painkill-0.0.1.dist-info/WHEEL
painkill-0.0.1.dist-info/licenses/LICENSE.txt
painkill-0.0.1.dist-info/RECORD
