Metadata-Version: 2.4
Name: painkill
Version: 0.0.1
Summary: Use Python for front end web development by generating html,css and javascript code
Project-URL: Homepage, https://github.com/Rubarion
Author-email: Sreehari P V <sreehari.mras@gmail.com>
License-File: LICENSE.txt
Classifier: License :: OSI Approved :: MIT License
Classifier: Operating System :: OS Independent
Classifier: Programming Language :: Python :: 3
Requires-Python: >=3
